h2hdb_komga/__init__.py
h2hdb_komga/__main__.py
h2hdb_komga/config_loader.py
h2hdb_komga/komga.py
h2hdb_komga/threading_tools.py
h2hdb_komga-0.0.1.dist-info/LICENSE
h2hdb_komga-0.0.1.dist-info/METADATA
h2hdb_komga-0.0.1.dist-info/WHEEL
h2hdb_komga-0.0.1.dist-info/top_level.txt
h2hdb_komga-0.0.1.dist-info/RECORD
