Metadata-Version: 2.2
Name: h2hdb-komga
Version: 0.0.1
Author: Kuan-Lun Wang
License: GNU Affero General Public License v3
Project-URL: Homepage, https://github.com/Kuan-Lun/h2hdb-komga
Project-URL: Source, https://github.com/Kuan-Lun/h2hdb-komga
Project-URL: Tracker, https://github.com/Kuan-Lun/h2hdb-komga/issues
Classifier: Development Status :: 3 - Alpha
Classifier: Intended Audience :: Developers
Classifier: Operating System :: OS Independent
Classifier: License :: OSI Approved :: GNU Affero General Public License v3 or later (AGPLv3+)
Classifier: Programming Language :: Python :: 3.13
License-File: LICENSE
Requires-Dist: h2hdb<2.0.0.0,>=0.7.0.9
Requires-Dist: requests<3.0.0,>=2.32.3
